{"User.232a5cbc-96cb-44db-a7c3-d2c0e1d342ce": {"id": "232a5cbc-96cb-44db-a7c3-d2c0e1d342ce", "created_at": "2025-01-17T11:16:14.798644", "updated_at": "2025-01-17T11:16:14.798653", "first_name": "Betty", "last_name": "Bar", "email": "airbnb@mail.com", "password": "root", "__class__": "User"}, "User.e5145b7b-14b7-4d0d-8f9d-e52d01133673": {"id": "e5145b7b-14b7-4d0d-8f9d-e52d01133673", "created_at": "2025-01-17T11:16:14.798873", "updated_at": "2025-01-17T11:16:14.798877", "first_name": "John", "email": "airbnb2@mail.com", "password": "root", "__class__": "User"}, "User.022fbef5-f195-4efa-9003-d7e9961b5747": {"id": "022fbef5-f195-4efa-9003-d7e9961b5747", "created_at": "2025-01-17T11:16:51.196856", "updated_at": "2025-01-17T11:16:51.196859", "first_name": "Betty", "last_name": "Bar", "email": "airbnb@mail.com", "password": "root", "__class__": "User"}, "User.ff2b14ba-2c6a-4629-916b-a00e8eed31b4": {"id": "ff2b14ba-2c6a-4629-916b-a00e8eed31b4", "created_at": "2025-01-17T11:16:51.197070", "updated_at": "2025-01-17T11:50:27.329894", "first_name": "Aimable_Nkurikiyimana", "email": "aimablenkurikiyimana@gmail.com", "password": "root", "__class__": "User"}, "User.da12850c-713c-472a-b205-96a1df366cd8": {"id": "da12850c-713c-472a-b205-96a1df366cd8", "created_at": "2025-01-17T11:20:08.083848", "updated_at": "2025-01-17T11:20:08.083890", "__class__": "User"}, "BaseModel.c28bed66-aa61-449b-8aa5-ea972a75fc26": {"id": "c28bed66-aa61-449b-8aa5-ea972a75fc26", "created_at": "2025-01-17T11:22:44.306312", "updated_at": "2025-01-17T11:22:44.306352", "__class__": "BaseModel"}, "BaseModel.44b3c5f7-1837-4d61-8645-bb91a9608c95": {"id": "44b3c5f7-1837-4d61-8645-bb91a9608c95", "created_at": "2025-01-17T11:31:21.883851", "updated_at": "2025-01-17T11:31:21.883893", "__class__": "BaseModel"}, "BaseModel.1ff005fa-9d2a-4d0e-9747-7712f3f63fb8": {"id": "1ff005fa-9d2a-4d0e-9747-7712f3f63fb8", "created_at": "2025-01-17T11:31:25.947538", "updated_at": "2025-01-17T11:31:25.947568", "__class__": "BaseModel"}}